setup.py
ml_utils/__init__.py
ml_utils/utils.py
py_ml_utils.egg-info/PKG-INFO
py_ml_utils.egg-info/SOURCES.txt
py_ml_utils.egg-info/dependency_links.txt
py_ml_utils.egg-info/requires.txt
py_ml_utils.egg-info/top_level.txt